{
  "Parcel": "198220-0815",
  "Name": "GRIMM WENDY J F+CHRISTOPHER",
  "Site Address": "323 NW 46TH ST 98107",
  "Residential Area": "082-002 (NW Appraisal District)",
  "Property Name": "",
  "Jurisdiction": "SEATTLE",
  "Levy Code": "0010",
  "Property Type": "R",
  "Plat Block / Building Number": "5",
  "Plat Lot / Unit Number": "12-13",
  "Quarter-Section-Township-Range": "SE-12-25-3",
  "Highest & Best Use As If Vacant": "MULTI-FAMILY DWELLING",
  "Highest & Best Use As Improved": "PRESENT USE",
  "Present Use": "Duplex",
  "Base Land Value SqFt": "0",
  "Base Land Value": "208,000",
  "% Base Land Value Impacted": "100",
  "Base Land Valued Date": "11/17/2009",
  "Base Land Value Tax Year": "2011",
  "Land SqFt": "5,141",
  "Acres": "0.12",
  "Percentage Unusable": "0",
  "Unbuildable": "NO",
  "Restrictive Size Shape": "NO",
  "Zoning": "SF 5000",
  "Water": "WATER DISTRICT",
  "Sewer/Septic": "PUBLIC",
  "Road Access": "PUBLIC",
  "Parking": "",
  "Street Surface": "PAVED",
  "Rainier": "",
  "Territorial": "",
  "Olympics": "",
  "Cascades": "",
  "Seattle Skyline": "",
  "Puget Sound": "",
  "Lake Washington": "",
  "Lake Sammamish": "",
  "Lake/River/Creek": "",
  "Other View": "",
  "Waterfront Location": "",
  "Waterfront Footage": " ",
  "Lot Depth Factor": " ",
  "Waterfront Bank": "",
  "Tide/Shore": "",
  "Waterfront Restricted Access": "",
  "Waterfront Access Rights": "NO",
  "Poor Quality": "",
  "Proximity Influence": "NO",
  "Historic Site": " ",
  "Current Use": " ",
  "Nbr Bldg Sites": " ",
  "Adjacent to Golf Fairway": "NO",
  "Adjacent to Greenbelt": "NO",
  "Other Designation": "NO",
  "Deed Restrictions": "NO",
  "Development Rights Purchased": "NO",
  "Easements": "NO",
  "Native Growth Protection Easement": "NO",
  "DNR Lease": "NO",
  "Topography": "NO",
  "Traffic Noise": "",
  "Airport Noise": " ",
  "Power Lines": "NO",
  "Other Nuisances": "NO",
  "Water Problems": "NO",
  "Transportation Concurrency": "NO",
  "Other Problems": "NO",
  "Environmental": "NO",
  "Building Number": "1",
  "Year Built": "1948",
  "Year Renovated": "0",
  "Stories": "1",
  "Living Units": "2",
  "Grade": "7  Average",
  "Grade Variant": "0",
  "Condition": "Good",
  "Basement Grade": "",
  "1st Floor": "1,330",
  "1/2 Floor": "0",
  "2nd Floor": "0",
  "Upper Floor": "0",
  "Finished Basement": "0",
  "Total Finished Area": "1,330",
  "Total Basement": "0",
  "Basement Garage": "0",
  "Unfinished 1/2": "0",
  "Unfinished Full": "0",
  "AGLA": "1,330",
  "Attached Garage": "0",
  "Bedrooms": "2",
  "Full Baths": "2",
  "3/4 Baths": "0",
  "1/2 Baths": "0",
  "Heat Source": "Gas",
  "Heat System": "Floor-Wall",
  "Deck Area SqFt": "0",
  "Open Porch SqFt": "110",
  "Enclosed Porch SqFt": "0",
  "Brick/Stone": "0",
  "Fireplace Single Story": "0",
  "Fireplace Muilti Story": "0",
  "Fireplace Free Standing": "0",
  "Fireplace Additional": "0",
  "AddnlCost": "0",
  "Obsolescence": "0",
  "Net Condition": "0",
  "Percentage Complete": "0",
  "Daylight Basement": " ",
  "View Utilization": " ",
  "sales": [
    {
      "Excise Number": "1858720",
      "Recording Number": "20011221001282",
      "Document Date": "12/19/2001",
      "Sale Price": "$0.00",
      "Seller Name": "GRIMM WENDY J FISHER",
      "Buyer Name": "GRIMM WENDY J F+GRIMM CHRISTOPHER A",
      "Instrument": "Quit Claim Deed",
      "Sale Reason": "Community Property Established"
    },
    {
      "Excise Number": "1256827",
      "Recording Number": "199207091861",
      "Document Date": "6/25/1992",
      "Sale Price": "$137,900.00",
      "Seller Name": "YOUNG ALFRED J+LESLIE L",
      "Buyer Name": "FISHER WENDY J",
      "Instrument": "Warranty Deed",
      "Sale Reason": "None"
    },
    {
      "Excise Number": "1245228",
      "Recording Number": "199205051260",
      "Document Date": "4/29/1992",
      "Sale Price": "$95,000.00",
      "Seller Name": "MADDOX ALICE J",
      "Buyer Name": "YOUNG ALFRED J+YOUNG LESLIE L",
      "Instrument": "Warranty Deed",
      "Sale Reason": "None"
    },
    {
      "Excise Number": "1231765",
      "Recording Number": "199202241444",
      "Document Date": "1/30/1992",
      "Sale Price": "$0.00",
      "Seller Name": "HARRELL ALFRED R JR+CECELIA",
      "Buyer Name": "MADDOX ALICE J",
      "Instrument": "Quit Claim Deed",
      "Sale Reason": "Other"
    }
  ],
  "tax_roll": [
    {
      "Account": "198220081501",
      "Valued Year": "2013",
      "Tax Year": "2014",
      "Omit Year": "",
      "Levy Code": "0010",
      "Appraised Land Value ($)": "204,000",
      "Appraised Imps Value ($)": "216,000",
      "Appraised Total Value ($)": "420,000",
      "New Dollars ($)": "0",
      "Taxable Land Value ($)": "204,000",
      "Taxable Imps Value ($)": "216,000",
      "Taxable Total Value ($)": "420,000",
      "Tax Value Reason": ""
    },
    {
      "Account": "198220081501",
      "Valued Year": "2012",
      "Tax Year": "2013",
      "Omit Year": "",
      "Levy Code": "0010",
      "Appraised Land Value ($)": "204,000",
      "Appraised Imps Value ($)": "220,000",
      "Appraised Total Value ($)": "424,000",
      "New Dollars ($)": "0",
      "Taxable Land Value ($)": "204,000",
      "Taxable Imps Value ($)": "220,000",
      "Taxable Total Value ($)": "424,000",
      "Tax Value Reason": ""
    },
    {
      "Account": "198220081501",
      "Valued Year": "2011",
      "Tax Year": "2012",
      "Omit Year": "",
      "Levy Code": "0010",
      "Appraised Land Value ($)": "208,000",
      "Appraised Imps Value ($)": "226,000",
      "Appraised Total Value ($)": "434,000",
      "New Dollars ($)": "0",
      "Taxable Land Value ($)": "208,000",
      "Taxable Imps Value ($)": "226,000",
      "Taxable Total Value ($)": "434,000",
      "Tax Value Reason": ""
    },
    {
      "Account": "198220081501",
      "Valued Year": "2010",
      "Tax Year": "2011",
      "Omit Year": "",
      "Levy Code": "0010",
      "Appraised Land Value ($)": "208,000",
      "Appraised Imps Value ($)": "232,000",
      "Appraised Total Value ($)": "440,000",
      "New Dollars ($)": "0",
      "Taxable Land Value ($)": "208,000",
      "Taxable Imps Value ($)": "232,000",
      "Taxable Total Value ($)": "440,000",
      "Tax Value Reason": ""
    },
    {
      "Account": "198220081501",
      "Valued Year": "2009",
      "Tax Year": "2010",
      "Omit Year": "",
      "Levy Code": "0010",
      "Appraised Land Value ($)": "172,000",
      "Appraised Imps Value ($)": "204,000",
      "Appraised Total Value ($)": "376,000",
      "New Dollars ($)": "0",
      "Taxable Land Value ($)": "172,000",
      "Taxable Imps Value ($)": "204,000",
      "Taxable Total Value ($)": "376,000",
      "Tax Value Reason": ""
    },
    {
      "Account": "198220081501",
      "Valued Year": "2008",
      "Tax Year": "2009",
      "Omit Year": "",
      "Levy Code": "0010",
      "Appraised Land Value ($)": "203,000",
      "Appraised Imps Value ($)": "254,000",
      "Appraised Total Value ($)": "457,000",
      "New Dollars ($)": "0",
      "Taxable Land Value ($)": "203,000",
      "Taxable Imps Value ($)": "254,000",
      "Taxable Total Value ($)": "457,000",
      "Tax Value Reason": ""
    },
    {
      "Account": "198220081501",
      "Valued Year": "2007",
      "Tax Year": "2008",
      "Omit Year": "",
      "Levy Code": "0010",
      "Appraised Land Value ($)": "185,000",
      "Appraised Imps Value ($)": "231,000",
      "Appraised Total Value ($)": "416,000",
      "New Dollars ($)": "0",
      "Taxable Land Value ($)": "185,000",
      "Taxable Imps Value ($)": "231,000",
      "Taxable Total Value ($)": "416,000",
      "Tax Value Reason": ""
    },
    {
      "Account": "198220081501",
      "Valued Year": "2006",
      "Tax Year": "2007",
      "Omit Year": "",
      "Levy Code": "0010",
      "Appraised Land Value ($)": "165,000",
      "Appraised Imps Value ($)": "205,000",
      "Appraised Total Value ($)": "370,000",
      "New Dollars ($)": "0",
      "Taxable Land Value ($)": "165,000",
      "Taxable Imps Value ($)": "205,000",
      "Taxable Total Value ($)": "370,000",
      "Tax Value Reason": ""
    },
    {
      "Account": "198220081501",
      "Valued Year": "2005",
      "Tax Year": "2006",
      "Omit Year": "",
      "Levy Code": "0010",
      "Appraised Land Value ($)": "157,000",
      "Appraised Imps Value ($)": "192,000",
      "Appraised Total Value ($)": "349,000",
      "New Dollars ($)": "0",
      "Taxable Land Value ($)": "157,000",
      "Taxable Imps Value ($)": "192,000",
      "Taxable Total Value ($)": "349,000",
      "Tax Value Reason": ""
    },
    {
      "Account": "198220081501",
      "Valued Year": "2004",
      "Tax Year": "2005",
      "Omit Year": "",
      "Levy Code": "0010",
      "Appraised Land Value ($)": "145,000",
      "Appraised Imps Value ($)": "172,000",
      "Appraised Total Value ($)": "317,000",
      "New Dollars ($)": "0",
      "Taxable Land Value ($)": "145,000",
      "Taxable Imps Value ($)": "172,000",
      "Taxable Total Value ($)": "317,000",
      "Tax Value Reason": ""
    },
    {
      "Account": "198220081501",
      "Valued Year": "2003",
      "Tax Year": "2004",
      "Omit Year": "",
      "Levy Code": "0010",
      "Appraised Land Value ($)": "137,000",
      "Appraised Imps Value ($)": "160,000",
      "Appraised Total Value ($)": "297,000",
      "New Dollars ($)": "0",
      "Taxable Land Value ($)": "137,000",
      "Taxable Imps Value ($)": "160,000",
      "Taxable Total Value ($)": "297,000",
      "Tax Value Reason": ""
    },
    {
      "Account": "198220081501",
      "Valued Year": "2002",
      "Tax Year": "2003",
      "Omit Year": "",
      "Levy Code": "0010",
      "Appraised Land Value ($)": "131,000",
      "Appraised Imps Value ($)": "133,000",
      "Appraised Total Value ($)": "264,000",
      "New Dollars ($)": "0",
      "Taxable Land Value ($)": "131,000",
      "Taxable Imps Value ($)": "133,000",
      "Taxable Total Value ($)": "264,000",
      "Tax Value Reason": ""
    },
    {
      "Account": "198220081501",
      "Valued Year": "2001",
      "Tax Year": "2002",
      "Omit Year": "",
      "Levy Code": "0010",
      "Appraised Land Value ($)": "120,000",
      "Appraised Imps Value ($)": "91,000",
      "Appraised Total Value ($)": "211,000",
      "New Dollars ($)": "0",
      "Taxable Land Value ($)": "120,000",
      "Taxable Imps Value ($)": "91,000",
      "Taxable Total Value ($)": "211,000",
      "Tax Value Reason": ""
    },
    {
      "Account": "198220081501",
      "Valued Year": "2000",
      "Tax Year": "2001",
      "Omit Year": "",
      "Levy Code": "0010",
      "Appraised Land Value ($)": "110,000",
      "Appraised Imps Value ($)": "69,000",
      "Appraised Total Value ($)": "179,000",
      "New Dollars ($)": "0",
      "Taxable Land Value ($)": "110,000",
      "Taxable Imps Value ($)": "69,000",
      "Taxable Total Value ($)": "179,000",
      "Tax Value Reason": ""
    },
    {
      "Account": "198220081501",
      "Valued Year": "1999",
      "Tax Year": "2000",
      "Omit Year": "",
      "Levy Code": "0010",
      "Appraised Land Value ($)": "92,000",
      "Appraised Imps Value ($)": "96,000",
      "Appraised Total Value ($)": "188,000",
      "New Dollars ($)": "0",
      "Taxable Land Value ($)": "92,000",
      "Taxable Imps Value ($)": "96,000",
      "Taxable Total Value ($)": "188,000",
      "Tax Value Reason": ""
    },
    {
      "Account": "198220081501",
      "Valued Year": "1998",
      "Tax Year": "1999",
      "Omit Year": "",
      "Levy Code": "0010",
      "Appraised Land Value ($)": "80,000",
      "Appraised Imps Value ($)": "97,000",
      "Appraised Total Value ($)": "177,000",
      "New Dollars ($)": "0",
      "Taxable Land Value ($)": "80,000",
      "Taxable Imps Value ($)": "97,000",
      "Taxable Total Value ($)": "177,000",
      "Tax Value Reason": ""
    },
    {
      "Account": "198220081501",
      "Valued Year": "1997",
      "Tax Year": "1998",
      "Omit Year": "",
      "Levy Code": "0010",
      "Appraised Land Value ($)": "0",
      "Appraised Imps Value ($)": "0",
      "Appraised Total Value ($)": "0",
      "New Dollars ($)": "0",
      "Taxable Land Value ($)": "70,000",
      "Taxable Imps Value ($)": "89,000",
      "Taxable Total Value ($)": "159,000",
      "Tax Value Reason": ""
    },
    {
      "Account": "198220081501",
      "Valued Year": "1996",
      "Tax Year": "1997",
      "Omit Year": "",
      "Levy Code": "0010",
      "Appraised Land Value ($)": "0",
      "Appraised Imps Value ($)": "0",
      "Appraised Total Value ($)": "0",
      "New Dollars ($)": "0",
      "Taxable Land Value ($)": "67,800",
      "Taxable Imps Value ($)": "41,400",
      "Taxable Total Value ($)": "109,200",
      "Tax Value Reason": ""
    },
    {
      "Account": "198220081501",
      "Valued Year": "1994",
      "Tax Year": "1995",
      "Omit Year": "",
      "Levy Code": "0010",
      "Appraised Land Value ($)": "0",
      "Appraised Imps Value ($)": "0",
      "Appraised Total Value ($)": "0",
      "New Dollars ($)": "0",
      "Taxable Land Value ($)": "67,800",
      "Taxable Imps Value ($)": "41,400",
      "Taxable Total Value ($)": "109,200",
      "Tax Value Reason": ""
    },
    {
      "Account": "198220081501",
      "Valued Year": "1992",
      "Tax Year": "1993",
      "Omit Year": "",
      "Levy Code": "0010",
      "Appraised Land Value ($)": "0",
      "Appraised Imps Value ($)": "0",
      "Appraised Total Value ($)": "0",
      "New Dollars ($)": "0",
      "Taxable Land Value ($)": "66,300",
      "Taxable Imps Value ($)": "54,800",
      "Taxable Total Value ($)": "121,100",
      "Tax Value Reason": ""
    },
    {
      "Account": "198220081501",
      "Valued Year": "1990",
      "Tax Year": "1991",
      "Omit Year": "",
      "Levy Code": "0010",
      "Appraised Land Value ($)": "0",
      "Appraised Imps Value ($)": "0",
      "Appraised Total Value ($)": "0",
      "New Dollars ($)": "0",
      "Taxable Land Value ($)": "60,800",
      "Taxable Imps Value ($)": "50,300",
      "Taxable Total Value ($)": "111,100",
      "Tax Value Reason": ""
    },
    {
      "Account": "198220081501",
      "Valued Year": "1988",
      "Tax Year": "1989",
      "Omit Year": "",
      "Levy Code": "0010",
      "Appraised Land Value ($)": "0",
      "Appraised Imps Value ($)": "0",
      "Appraised Total Value ($)": "0",
      "New Dollars ($)": "0",
      "Taxable Land Value ($)": "32,400",
      "Taxable Imps Value ($)": "39,500",
      "Taxable Total Value ($)": "71,900",
      "Tax Value Reason": ""
    },
    {
      "Account": "198220081501",
      "Valued Year": "1986",
      "Tax Year": "1987",
      "Omit Year": "",
      "Levy Code": "0010",
      "Appraised Land Value ($)": "0",
      "Appraised Imps Value ($)": "0",
      "Appraised Total Value ($)": "0",
      "New Dollars ($)": "0",
      "Taxable Land Value ($)": "32,000",
      "Taxable Imps Value ($)": "26,100",
      "Taxable Total Value ($)": "58,100",
      "Tax Value Reason": ""
    },
    {
      "Account": "198220081501",
      "Valued Year": "1984",
      "Tax Year": "1985",
      "Omit Year": "",
      "Levy Code": "0010",
      "Appraised Land Value ($)": "0",
      "Appraised Imps Value ($)": "0",
      "Appraised Total Value ($)": "0",
      "New Dollars ($)": "0",
      "Taxable Land Value ($)": "31,000",
      "Taxable Imps Value ($)": "32,300",
      "Taxable Total Value ($)": "63,300",
      "Tax Value Reason": ""
    },
    {
      "Account": "198220081501",
      "Valued Year": "1982",
      "Tax Year": "1983",
      "Omit Year": "",
      "Levy Code": "0010",
      "Appraised Land Value ($)": "0",
      "Appraised Imps Value ($)": "0",
      "Appraised Total Value ($)": "0",
      "New Dollars ($)": "0",
      "Taxable Land Value ($)": "31,000",
      "Taxable Imps Value ($)": "32,300",
      "Taxable Total Value ($)": "63,300",
      "Tax Value Reason": ""
    }
  ],
  "permits": [

  ]
}
