{
  "Parcel": "276780-0020",
  "Name": "WILCOX ANITA",
  "Site Address": "5900 8TH AVE NW 98107",
  "Residential Area": "082-002 (NW Appraisal District)",
  "Property Name": "",
  "Jurisdiction": "SEATTLE",
  "Levy Code": "0010",
  "Property Type": "R",
  "Plat Block / Building Number": "95",
  "Plat Lot / Unit Number": "4",
  "Quarter-Section-Township-Range": "NE-12-25-3",
  "Highest & Best Use As If Vacant": "MULTI-FAMILY DWELLING",
  "Highest & Best Use As Improved": "PRESENT USE",
  "Present Use": "Triplex",
  "Base Land Value SqFt": "0",
  "Base Land Value": "174,000",
  "% Base Land Value Impacted": "100",
  "Base Land Valued Date": "11/17/2009",
  "Base Land Value Tax Year": "2011",
  "Land SqFt": "4,650",
  "Acres": "0.11",
  "Percentage Unusable": "0",
  "Unbuildable": "NO",
  "Restrictive Size Shape": "NO",
  "Zoning": "SF 5000",
  "Water": "WATER DISTRICT",
  "Sewer/Septic": "PUBLIC",
  "Road Access": "PUBLIC",
  "Parking": "",
  "Street Surface": "PAVED",
  "Rainier": "",
  "Territorial": "",
  "Olympics": "",
  "Cascades": "",
  "Seattle Skyline": "",
  "Puget Sound": "",
  "Lake Washington": "",
  "Lake Sammamish": "",
  "Lake/River/Creek": "",
  "Other View": "",
  "Waterfront Location": "",
  "Waterfront Footage": " ",
  "Lot Depth Factor": " ",
  "Waterfront Bank": "",
  "Tide/Shore": "",
  "Waterfront Restricted Access": "",
  "Waterfront Access Rights": "NO",
  "Poor Quality": "",
  "Proximity Influence": "NO",
  "Historic Site": " ",
  "Current Use": " ",
  "Nbr Bldg Sites": " ",
  "Adjacent to Golf Fairway": "NO",
  "Adjacent to Greenbelt": "NO",
  "Other Designation": "NO",
  "Deed Restrictions": "NO",
  "Development Rights Purchased": "NO",
  "Easements": "NO",
  "Native Growth Protection Easement": "NO",
  "DNR Lease": "NO",
  "Topography": "NO",
  "Traffic Noise": "HIGH",
  "Airport Noise": " ",
  "Power Lines": "NO",
  "Other Nuisances": "NO",
  "Water Problems": "NO",
  "Transportation Concurrency": "NO",
  "Other Problems": "NO",
  "Environmental": "NO",
  "Building Number": "1",
  "Year Built": "1966",
  "Year Renovated": "0",
  "Stories": "1",
  "Living Units": "3",
  "Grade": "8  Good",
  "Grade Variant": "0",
  "Condition": "Good",
  "Basement Grade": "7  Average",
  "1st Floor": "1,700",
  "1/2 Floor": "0",
  "2nd Floor": "0",
  "Upper Floor": "0",
  "Finished Basement": "1,100",
  "Total Finished Area": "2,800",
  "Total Basement": "1,700",
  "Basement Garage": "550",
  "Unfinished 1/2": "0",
  "Unfinished Full": "0",
  "AGLA": "1,700",
  "Attached Garage": "0",
  "Bedrooms": "5",
  "Full Baths": "2",
  "3/4 Baths": "1",
  "1/2 Baths": "0",
  "Heat Source": "Gas",
  "Heat System": "Forced Air",
  "Deck Area SqFt": "0",
  "Open Porch SqFt": "0",
  "Enclosed Porch SqFt": "0",
  "Brick/Stone": "0",
  "Fireplace Single Story": "0",
  "Fireplace Muilti Story": "1",
  "Fireplace Free Standing": "0",
  "Fireplace Additional": "1",
  "AddnlCost": "0",
  "Obsolescence": "0",
  "Net Condition": "0",
  "Percentage Complete": "0",
  "Daylight Basement": " ",
  "View Utilization": " ",
  "sales": [
    {
      "Excise Number": "1663290",
      "Recording Number": "199901212259",
      "Document Date": "1/12/1999",
      "Sale Price": "$0.00",
      "Seller Name": "WILCOX ANITA L",
      "Buyer Name": "WILCOX ANITA L",
      "Instrument": "Quit Claim Deed",
      "Sale Reason": "Trust"
    },
    {
      "Excise Number": "1379631",
      "Recording Number": "199406130380",
      "Document Date": "6/8/1994",
      "Sale Price": "$220,000.00",
      "Seller Name": "CHAVEZ JANE M+MCELRATH EDITH",
      "Buyer Name": "WILCOX ANITA L",
      "Instrument": "Warranty Deed",
      "Sale Reason": "None"
    }
  ],
  "tax_roll": [
    {
      "Account": "276780002008",
      "Valued Year": "2013",
      "Tax Year": "2014",
      "Omit Year": "",
      "Levy Code": "0010",
      "Appraised Land Value ($)": "170,000",
      "Appraised Imps Value ($)": "360,000",
      "Appraised Total Value ($)": "530,000",
      "New Dollars ($)": "0",
      "Taxable Land Value ($)": "170,000",
      "Taxable Imps Value ($)": "360,000",
      "Taxable Total Value ($)": "530,000",
      "Tax Value Reason": ""
    },
    {
      "Account": "276780002008",
      "Valued Year": "2012",
      "Tax Year": "2013",
      "Omit Year": "",
      "Levy Code": "0010",
      "Appraised Land Value ($)": "170,000",
      "Appraised Imps Value ($)": "365,000",
      "Appraised Total Value ($)": "535,000",
      "New Dollars ($)": "0",
      "Taxable Land Value ($)": "170,000",
      "Taxable Imps Value ($)": "365,000",
      "Taxable Total Value ($)": "535,000",
      "Tax Value Reason": ""
    },
    {
      "Account": "276780002008",
      "Valued Year": "2011",
      "Tax Year": "2012",
      "Omit Year": "",
      "Levy Code": "0010",
      "Appraised Land Value ($)": "174,000",
      "Appraised Imps Value ($)": "373,000",
      "Appraised Total Value ($)": "547,000",
      "New Dollars ($)": "0",
      "Taxable Land Value ($)": "174,000",
      "Taxable Imps Value ($)": "373,000",
      "Taxable Total Value ($)": "547,000",
      "Tax Value Reason": ""
    },
    {
      "Account": "276780002008",
      "Valued Year": "2010",
      "Tax Year": "2011",
      "Omit Year": "",
      "Levy Code": "0010",
      "Appraised Land Value ($)": "174,000",
      "Appraised Imps Value ($)": "380,000",
      "Appraised Total Value ($)": "554,000",
      "New Dollars ($)": "0",
      "Taxable Land Value ($)": "174,000",
      "Taxable Imps Value ($)": "380,000",
      "Taxable Total Value ($)": "554,000",
      "Tax Value Reason": ""
    },
    {
      "Account": "276780002008",
      "Valued Year": "2009",
      "Tax Year": "2010",
      "Omit Year": "",
      "Levy Code": "0010",
      "Appraised Land Value ($)": "141,000",
      "Appraised Imps Value ($)": "335,000",
      "Appraised Total Value ($)": "476,000",
      "New Dollars ($)": "0",
      "Taxable Land Value ($)": "141,000",
      "Taxable Imps Value ($)": "335,000",
      "Taxable Total Value ($)": "476,000",
      "Tax Value Reason": ""
    },
    {
      "Account": "276780002008",
      "Valued Year": "2008",
      "Tax Year": "2009",
      "Omit Year": "",
      "Levy Code": "0010",
      "Appraised Land Value ($)": "166,000",
      "Appraised Imps Value ($)": "412,000",
      "Appraised Total Value ($)": "578,000",
      "New Dollars ($)": "0",
      "Taxable Land Value ($)": "166,000",
      "Taxable Imps Value ($)": "412,000",
      "Taxable Total Value ($)": "578,000",
      "Tax Value Reason": ""
    },
    {
      "Account": "276780002008",
      "Valued Year": "2007",
      "Tax Year": "2008",
      "Omit Year": "",
      "Levy Code": "0010",
      "Appraised Land Value ($)": "152,000",
      "Appraised Imps Value ($)": "374,000",
      "Appraised Total Value ($)": "526,000",
      "New Dollars ($)": "0",
      "Taxable Land Value ($)": "152,000",
      "Taxable Imps Value ($)": "374,000",
      "Taxable Total Value ($)": "526,000",
      "Tax Value Reason": ""
    },
    {
      "Account": "276780002008",
      "Valued Year": "2006",
      "Tax Year": "2007",
      "Omit Year": "",
      "Levy Code": "0010",
      "Appraised Land Value ($)": "136,000",
      "Appraised Imps Value ($)": "296,000",
      "Appraised Total Value ($)": "432,000",
      "New Dollars ($)": "0",
      "Taxable Land Value ($)": "136,000",
      "Taxable Imps Value ($)": "296,000",
      "Taxable Total Value ($)": "432,000",
      "Tax Value Reason": ""
    },
    {
      "Account": "276780002008",
      "Valued Year": "2005",
      "Tax Year": "2006",
      "Omit Year": "",
      "Levy Code": "0010",
      "Appraised Land Value ($)": "129,000",
      "Appraised Imps Value ($)": "291,000",
      "Appraised Total Value ($)": "420,000",
      "New Dollars ($)": "0",
      "Taxable Land Value ($)": "129,000",
      "Taxable Imps Value ($)": "291,000",
      "Taxable Total Value ($)": "420,000",
      "Tax Value Reason": ""
    },
    {
      "Account": "276780002008",
      "Valued Year": "2004",
      "Tax Year": "2005",
      "Omit Year": "",
      "Levy Code": "0010",
      "Appraised Land Value ($)": "118,000",
      "Appraised Imps Value ($)": "243,000",
      "Appraised Total Value ($)": "361,000",
      "New Dollars ($)": "0",
      "Taxable Land Value ($)": "118,000",
      "Taxable Imps Value ($)": "243,000",
      "Taxable Total Value ($)": "361,000",
      "Tax Value Reason": ""
    },
    {
      "Account": "276780002008",
      "Valued Year": "2003",
      "Tax Year": "2004",
      "Omit Year": "",
      "Levy Code": "0010",
      "Appraised Land Value ($)": "111,000",
      "Appraised Imps Value ($)": "232,000",
      "Appraised Total Value ($)": "343,000",
      "New Dollars ($)": "0",
      "Taxable Land Value ($)": "111,000",
      "Taxable Imps Value ($)": "232,000",
      "Taxable Total Value ($)": "343,000",
      "Tax Value Reason": ""
    },
    {
      "Account": "276780002008",
      "Valued Year": "2002",
      "Tax Year": "2003",
      "Omit Year": "",
      "Levy Code": "0010",
      "Appraised Land Value ($)": "81,000",
      "Appraised Imps Value ($)": "254,000",
      "Appraised Total Value ($)": "335,000",
      "New Dollars ($)": "0",
      "Taxable Land Value ($)": "81,000",
      "Taxable Imps Value ($)": "254,000",
      "Taxable Total Value ($)": "335,000",
      "Tax Value Reason": ""
    },
    {
      "Account": "276780002008",
      "Valued Year": "2001",
      "Tax Year": "2002",
      "Omit Year": "",
      "Levy Code": "0010",
      "Appraised Land Value ($)": "76,000",
      "Appraised Imps Value ($)": "234,000",
      "Appraised Total Value ($)": "310,000",
      "New Dollars ($)": "0",
      "Taxable Land Value ($)": "76,000",
      "Taxable Imps Value ($)": "234,000",
      "Taxable Total Value ($)": "310,000",
      "Tax Value Reason": ""
    },
    {
      "Account": "276780002008",
      "Valued Year": "2000",
      "Tax Year": "2001",
      "Omit Year": "",
      "Levy Code": "0010",
      "Appraised Land Value ($)": "69,000",
      "Appraised Imps Value ($)": "220,000",
      "Appraised Total Value ($)": "289,000",
      "New Dollars ($)": "0",
      "Taxable Land Value ($)": "69,000",
      "Taxable Imps Value ($)": "220,000",
      "Taxable Total Value ($)": "289,000",
      "Tax Value Reason": ""
    },
    {
      "Account": "276780002008",
      "Valued Year": "1999",
      "Tax Year": "2000",
      "Omit Year": "",
      "Levy Code": "0010",
      "Appraised Land Value ($)": "59,000",
      "Appraised Imps Value ($)": "212,000",
      "Appraised Total Value ($)": "271,000",
      "New Dollars ($)": "0",
      "Taxable Land Value ($)": "59,000",
      "Taxable Imps Value ($)": "212,000",
      "Taxable Total Value ($)": "271,000",
      "Tax Value Reason": ""
    },
    {
      "Account": "276780002008",
      "Valued Year": "1998",
      "Tax Year": "1999",
      "Omit Year": "",
      "Levy Code": "0010",
      "Appraised Land Value ($)": "56,000",
      "Appraised Imps Value ($)": "199,000",
      "Appraised Total Value ($)": "255,000",
      "New Dollars ($)": "0",
      "Taxable Land Value ($)": "56,000",
      "Taxable Imps Value ($)": "199,000",
      "Taxable Total Value ($)": "255,000",
      "Tax Value Reason": ""
    },
    {
      "Account": "276780002008",
      "Valued Year": "1997",
      "Tax Year": "1998",
      "Omit Year": "",
      "Levy Code": "0010",
      "Appraised Land Value ($)": "0",
      "Appraised Imps Value ($)": "0",
      "Appraised Total Value ($)": "0",
      "New Dollars ($)": "0",
      "Taxable Land Value ($)": "56,000",
      "Taxable Imps Value ($)": "154,000",
      "Taxable Total Value ($)": "210,000",
      "Tax Value Reason": ""
    },
    {
      "Account": "276780002008",
      "Valued Year": "1996",
      "Tax Year": "1997",
      "Omit Year": "",
      "Levy Code": "0010",
      "Appraised Land Value ($)": "0",
      "Appraised Imps Value ($)": "0",
      "Appraised Total Value ($)": "0",
      "New Dollars ($)": "0",
      "Taxable Land Value ($)": "56,000",
      "Taxable Imps Value ($)": "154,000",
      "Taxable Total Value ($)": "210,000",
      "Tax Value Reason": ""
    },
    {
      "Account": "276780002008",
      "Valued Year": "1994",
      "Tax Year": "1995",
      "Omit Year": "",
      "Levy Code": "0010",
      "Appraised Land Value ($)": "0",
      "Appraised Imps Value ($)": "0",
      "Appraised Total Value ($)": "0",
      "New Dollars ($)": "0",
      "Taxable Land Value ($)": "49,200",
      "Taxable Imps Value ($)": "87,300",
      "Taxable Total Value ($)": "136,500",
      "Tax Value Reason": ""
    },
    {
      "Account": "276780002008",
      "Valued Year": "1992",
      "Tax Year": "1993",
      "Omit Year": "",
      "Levy Code": "0010",
      "Appraised Land Value ($)": "0",
      "Appraised Imps Value ($)": "0",
      "Appraised Total Value ($)": "0",
      "New Dollars ($)": "0",
      "Taxable Land Value ($)": "54,800",
      "Taxable Imps Value ($)": "98,900",
      "Taxable Total Value ($)": "153,700",
      "Tax Value Reason": ""
    },
    {
      "Account": "276780002008",
      "Valued Year": "1990",
      "Tax Year": "1991",
      "Omit Year": "",
      "Levy Code": "0010",
      "Appraised Land Value ($)": "0",
      "Appraised Imps Value ($)": "0",
      "Appraised Total Value ($)": "0",
      "New Dollars ($)": "0",
      "Taxable Land Value ($)": "51,200",
      "Taxable Imps Value ($)": "92,400",
      "Taxable Total Value ($)": "143,600",
      "Tax Value Reason": ""
    },
    {
      "Account": "276780002008",
      "Valued Year": "1988",
      "Tax Year": "1989",
      "Omit Year": "",
      "Levy Code": "0010",
      "Appraised Land Value ($)": "0",
      "Appraised Imps Value ($)": "0",
      "Appraised Total Value ($)": "0",
      "New Dollars ($)": "0",
      "Taxable Land Value ($)": "29,300",
      "Taxable Imps Value ($)": "62,600",
      "Taxable Total Value ($)": "91,900",
      "Tax Value Reason": ""
    },
    {
      "Account": "276780002008",
      "Valued Year": "1986",
      "Tax Year": "1987",
      "Omit Year": "",
      "Levy Code": "0010",
      "Appraised Land Value ($)": "0",
      "Appraised Imps Value ($)": "0",
      "Appraised Total Value ($)": "0",
      "New Dollars ($)": "0",
      "Taxable Land Value ($)": "31,000",
      "Taxable Imps Value ($)": "43,300",
      "Taxable Total Value ($)": "74,300",
      "Tax Value Reason": ""
    },
    {
      "Account": "276780002008",
      "Valued Year": "1984",
      "Tax Year": "1985",
      "Omit Year": "",
      "Levy Code": "0010",
      "Appraised Land Value ($)": "0",
      "Appraised Imps Value ($)": "0",
      "Appraised Total Value ($)": "0",
      "New Dollars ($)": "0",
      "Taxable Land Value ($)": "31,000",
      "Taxable Imps Value ($)": "78,100",
      "Taxable Total Value ($)": "109,100",
      "Tax Value Reason": ""
    },
    {
      "Account": "276780002008",
      "Valued Year": "1982",
      "Tax Year": "1983",
      "Omit Year": "",
      "Levy Code": "0010",
      "Appraised Land Value ($)": "0",
      "Appraised Imps Value ($)": "0",
      "Appraised Total Value ($)": "0",
      "New Dollars ($)": "0",
      "Taxable Land Value ($)": "31,000",
      "Taxable Imps Value ($)": "78,100",
      "Taxable Total Value ($)": "109,100",
      "Tax Value Reason": ""
    }
  ],
  "permits": [

  ]
}
