{
  "Parcel": "276830-1324",
  "Name": "SCHUTT JAMES",
  "Site Address": "808 NW 51ST ST 98107",
  "Residential Area": "082-002 (NW Appraisal District)",
  "Property Name": "",
  "Jurisdiction": "SEATTLE",
  "Levy Code": "0010",
  "Property Type": "R",
  "Plat Block / Building Number": "151",
  "Plat Lot / Unit Number": "12-13",
  "Quarter-Section-Township-Range": "SW-12-25-3",
  "Highest & Best Use As If Vacant": "SINGLE FAMILY",
  "Highest & Best Use As Improved": "PRESENT USE",
  "Present Use": "Townhouse Plat",
  "Base Land Value SqFt": "0",
  "Base Land Value": "95,000",
  "% Base Land Value Impacted": "100",
  "Base Land Valued Date": "11/16/2009",
  "Base Land Value Tax Year": "2011",
  "Land SqFt": "1,606",
  "Acres": "0.04",
  "Percentage Unusable": "0",
  "Unbuildable": "NO",
  "Restrictive Size Shape": "NO",
  "Zoning": "LR1",
  "Water": "WATER DISTRICT",
  "Sewer/Septic": "PUBLIC",
  "Road Access": "PUBLIC",
  "Parking": "ADEQUATE",
  "Street Surface": "PAVED",
  "Rainier": "",
  "Territorial": "",
  "Olympics": "",
  "Cascades": "",
  "Seattle Skyline": "",
  "Puget Sound": "",
  "Lake Washington": "",
  "Lake Sammamish": "",
  "Lake/River/Creek": "",
  "Other View": "",
  "Waterfront Location": "",
  "Waterfront Footage": " ",
  "Lot Depth Factor": " ",
  "Waterfront Bank": "",
  "Tide/Shore": "",
  "Waterfront Restricted Access": "",
  "Waterfront Access Rights": "NO",
  "Poor Quality": "",
  "Proximity Influence": "NO",
  "Historic Site": " ",
  "Current Use": " ",
  "Nbr Bldg Sites": " ",
  "Adjacent to Golf Fairway": "NO",
  "Adjacent to Greenbelt": "NO",
  "Other Designation": "NO",
  "Deed Restrictions": "NO",
  "Development Rights Purchased": "NO",
  "Easements": "NO",
  "Native Growth Protection Easement": "NO",
  "DNR Lease": "NO",
  "Topography": "NO",
  "Traffic Noise": "",
  "Airport Noise": " ",
  "Power Lines": "NO",
  "Other Nuisances": "NO",
  "Water Problems": "NO",
  "Transportation Concurrency": "NO",
  "Other Problems": "NO",
  "Environmental": "NO",
  "Building Number": "1",
  "Year Built": "2006",
  "Year Renovated": "0",
  "Stories": "3",
  "Living Units": "1",
  "Grade": "8  Good",
  "Grade Variant": "0",
  "Condition": "Average",
  "Basement Grade": "",
  "1st Floor": "320",
  "1/2 Floor": "0",
  "2nd Floor": "710",
  "Upper Floor": "710",
  "Finished Basement": "0",
  "Total Finished Area": "1,740",
  "Total Basement": "0",
  "Basement Garage": "0",
  "Unfinished 1/2": "0",
  "Unfinished Full": "0",
  "AGLA": "1,740",
  "Attached Garage": "210",
  "Bedrooms": "3",
  "Full Baths": "3",
  "3/4 Baths": "0",
  "1/2 Baths": "1",
  "Heat Source": "Gas",
  "Heat System": "Floor-Wall",
  "Deck Area SqFt": "130",
  "Open Porch SqFt": "80",
  "Enclosed Porch SqFt": "0",
  "Brick/Stone": "0",
  "Fireplace Single Story": "1",
  "Fireplace Muilti Story": "0",
  "Fireplace Free Standing": "0",
  "Fireplace Additional": "0",
  "AddnlCost": "0",
  "Obsolescence": "0",
  "Net Condition": "0",
  "Percentage Complete": "0",
  "Daylight Basement": " ",
  "View Utilization": " ",
  "sales": [
    {
      "Excise Number": "2464971",
      "Recording Number": "20101029003092",
      "Document Date": "10/22/2010",
      "Sale Price": "$419,000.00",
      "Seller Name": "FARAONE TROY",
      "Buyer Name": "SCHUTT JAMES",
      "Instrument": "Statutory Warranty Deed",
      "Sale Reason": "None"
    },
    {
      "Excise Number": "2249643",
      "Recording Number": "20061114002462",
      "Document Date": "11/10/2006",
      "Sale Price": "$479,000.00",
      "Seller Name": "AA ASHWORTH DEVELOPMENT L L C",
      "Buyer Name": "FARAONE TROY",
      "Instrument": "Statutory Warranty Deed",
      "Sale Reason": "None"
    },
    {
      "Excise Number": "2249650",
      "Recording Number": "20061114002463",
      "Document Date": "11/10/2006",
      "Sale Price": "$0.00",
      "Seller Name": "ROUSH CHRISTINE L",
      "Buyer Name": "FARAONE TROY E",
      "Instrument": "Quit Claim Deed",
      "Sale Reason": "Property Settlement"
    }
  ],
  "tax_roll": [
    {
      "Account": "276830132409",
      "Valued Year": "2013",
      "Tax Year": "2014",
      "Omit Year": "",
      "Levy Code": "0010",
      "Appraised Land Value ($)": "93,000",
      "Appraised Imps Value ($)": "320,000",
      "Appraised Total Value ($)": "413,000",
      "New Dollars ($)": "0",
      "Taxable Land Value ($)": "93,000",
      "Taxable Imps Value ($)": "320,000",
      "Taxable Total Value ($)": "413,000",
      "Tax Value Reason": ""
    },
    {
      "Account": "276830132409",
      "Valued Year": "2012",
      "Tax Year": "2013",
      "Omit Year": "",
      "Levy Code": "0010",
      "Appraised Land Value ($)": "93,000",
      "Appraised Imps Value ($)": "270,000",
      "Appraised Total Value ($)": "363,000",
      "New Dollars ($)": "0",
      "Taxable Land Value ($)": "93,000",
      "Taxable Imps Value ($)": "270,000",
      "Taxable Total Value ($)": "363,000",
      "Tax Value Reason": ""
    },
    {
      "Account": "276830132409",
      "Valued Year": "2011",
      "Tax Year": "2012",
      "Omit Year": "",
      "Levy Code": "0010",
      "Appraised Land Value ($)": "95,000",
      "Appraised Imps Value ($)": "276,000",
      "Appraised Total Value ($)": "371,000",
      "New Dollars ($)": "0",
      "Taxable Land Value ($)": "95,000",
      "Taxable Imps Value ($)": "276,000",
      "Taxable Total Value ($)": "371,000",
      "Tax Value Reason": ""
    },
    {
      "Account": "276830132409",
      "Valued Year": "2010",
      "Tax Year": "2011",
      "Omit Year": "",
      "Levy Code": "0010",
      "Appraised Land Value ($)": "95,000",
      "Appraised Imps Value ($)": "269,000",
      "Appraised Total Value ($)": "364,000",
      "New Dollars ($)": "0",
      "Taxable Land Value ($)": "95,000",
      "Taxable Imps Value ($)": "269,000",
      "Taxable Total Value ($)": "364,000",
      "Tax Value Reason": ""
    },
    {
      "Account": "276830132409",
      "Valued Year": "2009",
      "Tax Year": "2010",
      "Omit Year": "",
      "Levy Code": "0010",
      "Appraised Land Value ($)": "96,000",
      "Appraised Imps Value ($)": "260,000",
      "Appraised Total Value ($)": "356,000",
      "New Dollars ($)": "0",
      "Taxable Land Value ($)": "96,000",
      "Taxable Imps Value ($)": "260,000",
      "Taxable Total Value ($)": "356,000",
      "Tax Value Reason": ""
    },
    {
      "Account": "276830132409",
      "Valued Year": "2008",
      "Tax Year": "2009",
      "Omit Year": "",
      "Levy Code": "0010",
      "Appraised Land Value ($)": "114,000",
      "Appraised Imps Value ($)": "365,000",
      "Appraised Total Value ($)": "479,000",
      "New Dollars ($)": "0",
      "Taxable Land Value ($)": "114,000",
      "Taxable Imps Value ($)": "365,000",
      "Taxable Total Value ($)": "479,000",
      "Tax Value Reason": ""
    },
    {
      "Account": "276830132409",
      "Valued Year": "2007",
      "Tax Year": "2008",
      "Omit Year": "",
      "Levy Code": "0010",
      "Appraised Land Value ($)": "104,000",
      "Appraised Imps Value ($)": "386,000",
      "Appraised Total Value ($)": "490,000",
      "New Dollars ($)": "50,000",
      "Taxable Land Value ($)": "104,000",
      "Taxable Imps Value ($)": "386,000",
      "Taxable Total Value ($)": "490,000",
      "Tax Value Reason": ""
    },
    {
      "Account": "276830132409",
      "Valued Year": "2006",
      "Tax Year": "2007",
      "Omit Year": "",
      "Levy Code": "0010",
      "Appraised Land Value ($)": "99,000",
      "Appraised Imps Value ($)": "287,000",
      "Appraised Total Value ($)": "386,000",
      "New Dollars ($)": "386,000",
      "Taxable Land Value ($)": "99,000",
      "Taxable Imps Value ($)": "287,000",
      "Taxable Total Value ($)": "386,000",
      "Tax Value Reason": ""
    },
    {
      "Account": "276830132409",
      "Valued Year": "2005",
      "Tax Year": "2006",
      "Omit Year": "",
      "Levy Code": "0010",
      "Appraised Land Value ($)": "0",
      "Appraised Imps Value ($)": "0",
      "Appraised Total Value ($)": "0",
      "New Dollars ($)": "0",
      "Taxable Land Value ($)": "75,500",
      "Taxable Imps Value ($)": "0",
      "Taxable Total Value ($)": "75,500",
      "Tax Value Reason": ""
    }
  ],
  "permits": [

  ]
}
